publishing_test/__init__.py
publishing_test/cli.py
publishing_test/publishing_test.py
publishing_test-0.1.1.dist-info/LICENSE
publishing_test-0.1.1.dist-info/METADATA
publishing_test-0.1.1.dist-info/WHEEL
publishing_test-0.1.1.dist-info/entry_points.txt
publishing_test-0.1.1.dist-info/RECORD
