Metadata-Version: 2.1
Name: publishing_test
Version: 0.1.1
Summary: Python Boilerplate contains all the boilerplate you need to create a Python package.
Home-page: https://gitlab.com/paul_armstrong/publishing_test
Keywords: publishing_test
Author: Paul Armstrong
Requires-Python: >=3.10,<4.0
Classifier: Development Status :: 2 - Pre-Alpha
Classifier: Intended Audience :: Developers
Classifier: License :: OSI Approved :: MIT License
Classifier: Natural Language :: English
Classifier: Programming Language :: Python :: 3
Classifier: Programming Language :: Python :: 3.10
Classifier: Programming Language :: Python :: 3.11
Classifier: Programming Language :: Python :: 3.12
Classifier: Programming Language :: Python :: 3.6
Classifier: Programming Language :: Python :: 3.7
Classifier: Programming Language :: Python :: 3.8
Classifier: Programming Language :: Python :: 3.9
Requires-Dist: click
Project-URL: Repository, https://gitlab.com/paul_armstrong/publishing_test
